glob_linters/__init__.py
glob_linters/cli.py
glob_linters/linters.py
glob_linters/utils/__init__.py
glob_linters/utils/io.py
glob_linters/utils/settings.py
glob_linters-0.3.1.dist-info/AUTHORS.rst
glob_linters-0.3.1.dist-info/LICENSE
glob_linters-0.3.1.dist-info/METADATA
glob_linters-0.3.1.dist-info/WHEEL
glob_linters-0.3.1.dist-info/entry_points.txt
glob_linters-0.3.1.dist-info/top_level.txt
glob_linters-0.3.1.dist-info/RECORD
