Metadata-Version: 2.1
Name: glob-linters
Version: 0.3.1
Summary: Integrated tool for multi-language linters for command line tooland GitHub action
Home-page: https://github.com/bowentan/glob-linters
Author: Bowen Tan
Author-email: bowentan78@gmail.com
License: MIT license
Keywords: glob-linters
Classifier: Development Status :: 2 - Pre-Alpha
Classifier: Intended Audience :: Developers
Classifier: License :: OSI Approved :: MIT License
Classifier: Natural Language :: English
Classifier: Programming Language :: Python :: 3
Classifier: Programming Language :: Python :: 3.6
Classifier: Programming Language :: Python :: 3.7
Classifier: Programming Language :: Python :: 3.8
Requires-Python: >=3.6
License-File: LICENSE
License-File: AUTHORS.rst
Requires-Dist: clang-format (==14.0.6)
Requires-Dist: cpplint (==1.6.1)
Requires-Dist: pylint (==2.15.7)
Requires-Dist: flake8 (==5.0.4)
Requires-Dist: black (==22.10.0)
Requires-Dist: isort (==5.10.1)
Requires-Dist: mypy (==0.991)
